winrt/_winrt_microsoft_ui_input_interop.cp312-win32.pyd
winrt/_winrt_microsoft_ui_input_interop.pyi
winrt/microsoft/ui/input/interop/__init__.py
winrt/microsoft/ui/input/interop/py.typed
winrt_Microsoft.UI.Input.Interop-2.3.0.dist-info/METADATA
winrt_Microsoft.UI.Input.Interop-2.3.0.dist-info/WHEEL
winrt_Microsoft.UI.Input.Interop-2.3.0.dist-info/top_level.txt
winrt_Microsoft.UI.Input.Interop-2.3.0.dist-info/RECORD
