Metadata-Version: 2.1
Name: winrt-Microsoft.UI.Input.Interop
Version: 2.3.0
Summary: Python projection of Windows Runtime (WinRT) APIs
License: MIT
Project-URL: Documentation, https://pywinrt.readthedocs.io
Project-URL: Repository, https://github.com/pywinrt/pywinrt
Project-URL: Changelog, https://github.com/pywinrt/pywinrt/blob/main/CHANGELOG.md
Classifier: Operating System :: Microsoft :: Windows
Classifier: Programming Language :: Python :: 3
Classifier: Programming Language :: Python :: Implementation :: CPython
Classifier: Intended Audience :: Developers
Requires-Python: <3.14,>=3.9
Requires-Dist: winrt-runtime==2.3.0
Provides-Extra: all
Requires-Dist: winrt-Microsoft.UI.Input[all]==2.3.0; extra == "all"
Requires-Dist: winrt-Windows.Devices.Input[all]==2.3.0; extra == "all"
